LICENSE.md
README.md
pyproject.toml
setup.py
galaxie_shell.egg-info/PKG-INFO
galaxie_shell.egg-info/SOURCES.txt
galaxie_shell.egg-info/dependency_links.txt
galaxie_shell.egg-info/entry_points.txt
galaxie_shell.egg-info/requires.txt
galaxie_shell.egg-info/top_level.txt
glxshell/__init__.py
glxshell/glxsh.py
glxshell/glxush.py
glxshell/lib/__init__.py
glxshell/lib/alias.py
glxshell/lib/cmd.py
glxshell/lib/columnize.py
glxshell/lib/command.py
glxshell/lib/completers.py
glxshell/lib/environ.py
glxshell/lib/iso8601.py
glxshell/lib/path.py
glxshell/lib/stat.py
glxshell/lib/symbolic_mode.py
glxshell/lib/tabulate.py
glxshell/lib/ush.py
glxshell/lib/utils.py
glxshell/utilities/__init__.py
glxshell/utilities/alias.py
glxshell/utilities/basename.py
glxshell/utilities/cat.py
glxshell/utilities/cd.py
glxshell/utilities/chmod.py
glxshell/utilities/clear.py
glxshell/utilities/cp.py
glxshell/utilities/date.py
glxshell/utilities/df.py
glxshell/utilities/dirname.py
glxshell/utilities/du.py
glxshell/utilities/echo.py
glxshell/utilities/env.py
glxshell/utilities/exit.py
glxshell/utilities/false.py
glxshell/utilities/head.py
glxshell/utilities/ls.py
glxshell/utilities/mkdir.py
glxshell/utilities/mv.py
glxshell/utilities/pwd.py
glxshell/utilities/rm.py
glxshell/utilities/rmdir.py
glxshell/utilities/sleep.py
glxshell/utilities/tail.py
glxshell/utilities/tee.py
glxshell/utilities/time.py
glxshell/utilities/touch.py
glxshell/utilities/true.py
glxshell/utilities/tty.py
glxshell/utilities/umask.py
glxshell/utilities/unalias.py
glxshell/utilities/uname.py