Metadata-Version: 2.1
Name: galaxie-shell
Version: 0.2.6
Summary: Galaxie Shell is a autonomous shell ready for CI and low tech OS
Author: Tuuux
Project-URL: Homepage, https://codeberg.org/Tuuux/galaxie-shell
Project-URL: Issues, https://codeberg.org/Tuuux/galaxie-shell/-/issues
Project-URL: Readthedocs, http://galaxie-shell.readthedocs.io
Keywords: Galaxie,SHELL,POSIX,Micropython
Classifier: Environment :: Console
Classifier: License :: Public Domain
Classifier: Topic :: Software Development :: Libraries :: Python Modules
Classifier: Programming Language :: Python
Classifier: Programming Language :: Python :: 3 :: Only
Requires-Python: >=3.0
License-File: LICENSE.md
Requires-Dist: wheel
Requires-Dist: setuptools
Provides-Extra: tests
Requires-Dist: coverage; extra == "tests"
Requires-Dist: setuptools; extra == "tests"
Requires-Dist: wheel; extra == "tests"
Requires-Dist: mock<4,>=1.0.1; python_version < "3.4" and extra == "tests"
